ALU_RISCV.v
`timescale 1ns / 1ps

module Alu_riscv(
    input [31:0] a,
    input [31:0] b,
    input [4:0] aluOp,
    output reg flag,
    output reg [31:0] result 
    );
    
    `define ALU_ADD 5'b00000
    `define ALU_SUB 5'b00001 
    `define ALU_XOR 5'b00010
    `define ALU_OR  5'b00011
    `define ALU_AND 5'b00100  
    `define ALU_SRA 5'b00101
    `define ALU_SRL 5'b00110
    `define ALU_SLL 5'b00111
    `define ALU_LTS 5'b01000
    `define ALU_LTU 5'b01001
    `define ALU_GES 5'b01010
    `define ALU_GEU 5'b01011
    `define ALU_EQ  5'b01100
    `define ALU_NE  5'b01101      
    
    always @ (*) begin
        case(aluOp)
            `ALU_ADD : begin result = a + b; flag = 0; end
            `ALU_SUB : begin result = a - b; flag = 0; end
            `ALU_XOR : begin result = a ^ b; flag = 0; end
            `ALU_OR : begin result = a | b; flag = 0; end
            `ALU_AND : begin result = a & b; flag = 0; end
            `ALU_SRA : begin result = a >>> b; flag = 0; end
            `ALU_SRL : begin result = a >> b; flag = 0; end
            `ALU_SLL : begin result = a << b; flag = 0; end
            `ALU_LTS : begin result = $signed(a) < $signed(b); flag = ($signed(a) < $signed(b)); end
            `ALU_LTU : begin result = a < b; flag = (a < b); end
            `ALU_GES : begin result = $signed(a) >= $signed(b); flag = ($signed(a) >= $signed(b)); end
            `ALU_GEU : begin result = a >= b; flag = (a >= b); end
            `ALU_EQ : begin result = a == b; flag = (a == b); end
            `ALU_NE : begin result = a != b; flag = (a != b); end
            default: begin result = 6'hxx; flag = 1'bx; end
        endcase
    end
    
endmodule

RF.v
`timescale 1ns / 1ps

module RF(
    input clk, //Clock signal
    input we3, //Write Enable 
    input [4:0] a1, //Adress port 1
    input [4:0] a2, //Adress port 2
    input [4:0] a3, //Adress port 3
    input [31:0] wd3, //Write Data
    input rst,
    
    output [31:0] rd1, //Read Data1
    output [31:0] rd2 //Read Data1
    );
    
    //Main register
    reg [31:0] rf [0:31];

    assign rd1 = (a1 != 0) ? rf[a1] : 0;
    assign rd2 = (a2 != 0) ? rf[a2] : 0;   
 
    integer i;

    always @ (posedge clk)
        if (rst) begin 
            for (i=0; i<31; i=i+1) begin
               rf[i] <= 32'd0;
            end
        end 
        else begin
            if (we3) rf[a3] <= wd3;
        end
        

endmodule

instruction_memory.v
`timescale 1ns / 1ps


module instruction_memory(
    input [7:0] a,
    output [31:0] rd
    );
    
    initial $readmemb("file_name", reg_name);
    reg [31:0] reg_name [63:0];
    
    assign rd = reg_name[a];
    
endmodule

microarchitecture.v
`timescale 1ns / 1ps

`include "instruction_memory.v"
`include "ALU_RISCV.v"
`include "RF.v"

module microarchitecture(
    input clk,
    input rst,

    output [31:0] out
);

    wire [31:0] instr; //All instruction

    //Write enable
    wire we3; 
    assign we3 = instr[29] | instr [28]; 
    
    wire [31:0] rd1; //Read data from RF port 1
    wire [31:0] rd2; //Read data from RF port 2
    reg [31:0] wd3; //Write data from RF port 3
    
    reg [7:0] pc; //Register for Program Counter
    
    wire [31:0] aluResult; //ALU result
    wire flag; //ALU flag

    assign out = aluResult[31:0];
   
    
    wire [1:0] pcOp;
    assign pcOp = ((flag & instr[30])) | instr[31];
    reg [7:0] pcInput;
    
    //Work with program counter
    always @ (*) begin
        case(pcOp)
            2'b0: begin pcInput = 8'h1; end
            2'b1: begin pcInput = instr[12:5]; end
        endcase    
    end
    
    //Increase program counter
    always @ (posedge clk) begin
        pc <= pc + pcInput;
    end

    //Reset program counter
    always @ (posedge rst) begin
        pc <= 0;
    end
    
    //Instantiation of modules ALU, RF, Instruction memory
    instruction_memory IM (pc, instr);
    RF finalRF(clk, we3, instr[22:18], instr[17:13], instr[4:0], wd3, rst, rd1, rd2);
    Alu_riscv ALU(rd1, rd2, instr[27:23], flag, aluResult);
    
    //Work with write data
    wire [1:0] wdOp = instr[29:28];
    wire [31:0] seConst = {{24{instr[12]}}, instr[12:5]}; // <--- SE block realization
    
    //Multiplexor for write register file
    always @ (*) begin
        case(wdOp)
            2'd1: begin assign wd3 = aluResult; end
            2'd2: begin assign wd3 = seConst; end
        endcase
    end
    
endmodule

microarchitecture_tb.v
`timescale 1ns / 1ps
`include "microarchitecture.v"

module microarchitecture_tb();

    reg clk = 1'b1;
    always #1 clk = !clk;

    reg rst = 1'b1;
    
    wire [31:0] out;

    microarchitecture microarchitecture(clk, rst, out);

    initial begin
        rst = 1'b0;
        $dumpfile("microarchitecture_tb.vcd");
        $dumpvars;
        #128 $finish;
    end
endmodule

microarchitecture_tb.vcd
$date
	Thu Nov 18 02:09:22 2021
$end
$version
	Icarus Verilog
$end
$timescale
	1ps
$end
$scope module microarchitecture_tb $end
$var wire 32 ! out [31:0] $end
$var reg 1 " clk $end
$var reg 1 # rst $end
$scope module microarchitecture $end
$var wire 1 " clk $end
$var wire 32 $ out [31:0] $end
$var wire 2 % pcOp [1:0] $end
$var wire 1 # rst $end
$var wire 1 & we3 $end
$var wire 2 ' wdOp [1:0] $end
$var wire 32 ( seConst [31:0] $end
$var wire 32 ) rd2 [31:0] $end
$var wire 32 * rd1 [31:0] $end
$var wire 32 + instr [31:0] $end
$var wire 1 , flag $end
$var wire 32 - aluResult [31:0] $end
$var reg 8 . pc [7:0] $end
$var reg 8 / pcInput [7:0] $end
$var reg 32 0 wd3 [31:0] $end
$scope module ALU $end
$var wire 5 1 aluOp [4:0] $end
$var wire 32 2 b [31:0] $end
$var wire 32 3 a [31:0] $end
$var reg 1 , flag $end
$var reg 32 4 result [31:0] $end
$upscope $end
$scope module IM $end
$var wire 8 5 a [7:0] $end
$var wire 32 6 rd [31:0] $end
$upscope $end
$scope module finalRF $end
$var wire 5 7 a1 [4:0] $end
$var wire 5 8 a2 [4:0] $end
$var wire 5 9 a3 [4:0] $end
$var wire 1 " clk $end
$var wire 1 # rst $end
$var wire 32 : wd3 [31:0] $end
$var wire 1 & we3 $end
$var wire 32 ; rd2 [31:0] $end
$var wire 32 < rd1 [31:0] $end
$var integer 32 = i [31:0] $end
$upscope $end
$upscope $end
$upscope $end
$enddefinitions $end
#0
$dumpvars
bx =
b0 <
b0 ;
b1 :
b1 9
b0 8
b0 7
b10100000000000000000000000100001 6
b0 5
b0 4
b0 3
b0 2
b0 1
b1 0
b1 /
b0 .
b0 -
0,
b10100000000000000000000000100001 +
b0 *
b0 )
b1 (
b10 '
1&
b1 %
b0 $
0#
1"
b0 !
$end
#1000
0"
#2000
b10 9
b10100000000000000000000000100010 +
b10100000000000000000000000100010 6
b1 .
b1 5
1"
#3000
0"
#4000
b10 !
b10 $
b10 -
b10 4
b1 )
b1 2
b1 ;
b1 *
b1 3
b1 <
0&
b0 '
b11 9
b10 8
b1 7
b10000000000001000100000000100011 +
b10000000000001000100000000100011 6
b10 .
b10 5
1"
#5000
0"
#6000
b0 !
b0 $
b0 -
b0 4
b0 )
b0 2
b0 ;
b0 *
b0 3
b0 <
b0 %
b0 0
b0 :
b0 (
b0 9
b0 8
b0 7
b1 /
b0 +
b0 6
b11 .
b11 5
1"
#7000
0"
#8000
b100 .
b100 5
1"
#9000
0"
#10000
b101 .
b101 5
1"
#11000
0"
#12000
b110 .
b110 5
1"
#13000
0"
#14000
b111 .
b111 5
1"
#15000
0"
#16000
b1000 .
b1000 5
1"
#17000
0"
#18000
b1001 .
b1001 5
1"
#19000
0"
#20000
b1010 .
b1010 5
1"
#21000
0"
#22000
b1011 .
b1011 5
1"
#23000
0"
#24000
b1100 .
b1100 5
1"
#25000
0"
#26000
b1101 .
b1101 5
1"
#27000
0"
#28000
b1110 .
b1110 5
1"
#29000
0"
#30000
b1111 .
b1111 5
1"
#31000
0"
#32000
b10000 .
b10000 5
1"
#33000
0"
#34000
b10001 .
b10001 5
1"
#35000
0"
#36000
b10010 .
b10010 5
1"
#37000
0"
#38000
b10011 .
b10011 5
1"
#39000
0"
#40000
b10100 .
b10100 5
1"
#41000
0"
#42000
b10101 .
b10101 5
1"
#43000
0"
#44000
b10110 .
b10110 5
1"
#45000
0"
#46000
b10111 .
b10111 5
1"
#47000
0"
#48000
b11000 .
b11000 5
1"
#49000
0"
#50000
b11001 .
b11001 5
1"
#51000
0"
#52000
b11010 .
b11010 5
1"
#53000
0"
#54000
b11011 .
b11011 5
1"
#55000
0"
#56000
b11100 .
b11100 5
1"
#57000
0"
#58000
b11101 .
b11101 5
1"
#59000
0"
#60000
b11110 .
b11110 5
1"
#61000
0"
#62000
b11111 .
b11111 5
1"
#63000
0"
#64000
b100000 .
b100000 5
1"
#65000
0"
#66000
b100001 .
b100001 5
1"
#67000
0"
#68000
b100010 .
b100010 5
1"
#69000
0"
#70000
b100011 .
b100011 5
1"
#71000
0"
#72000
b100100 .
b100100 5
1"
#73000
0"
#74000
b100101 .
b100101 5
1"
#75000
0"
#76000
b100110 .
b100110 5
1"
#77000
0"
#78000
b100111 .
b100111 5
1"
#79000
0"
#80000
b101000 .
b101000 5
1"
#81000
0"
#82000
b101001 .
b101001 5
1"
#83000
0"
#84000
b101010 .
b101010 5
1"
#85000
0"
#86000
b101011 .
b101011 5
1"
#87000
0"
#88000
b101100 .
b101100 5
1"
#89000
0"
#90000
b101101 .
b101101 5
1"
#91000
0"
#92000
b101110 .
b101110 5
1"
#93000
0"
#94000
b101111 .
b101111 5
1"
#95000
0"
#96000
b110000 .
b110000 5
1"
#97000
0"
#98000
b110001 .
b110001 5
1"
#99000
0"
#100000
b110010 .
b110010 5
1"
#101000
0"
#102000
b110011 .
b110011 5
1"
#103000
0"
#104000
b110100 .
b110100 5
1"
#105000
0"
#106000
b110101 .
b110101 5
1"
#107000
0"
#108000
b110110 .
b110110 5
1"
#109000
0"
#110000
b110111 .
b110111 5
1"
#111000
0"
#112000
b111000 .
b111000 5
1"
#113000
0"
#114000
b111001 .
b111001 5
1"
#115000
0"
#116000
b111010 .
b111010 5
1"
#117000
0"
#118000
b111011 .
b111011 5
1"
#119000
0"
#120000
b111100 .
b111100 5
1"
#121000
0"
#122000
b111101 .
b111101 5
1"
#123000
0"
#124000
b111110 .
b111110 5
1"
#125000
0"
#126000
b111111 .
b111111 5
1"
#127000
0"
#128000
x,
b0xxxxxx !
b0xxxxxx $
b0xxxxxx -
b0xxxxxx 4
bx )
bx 2
bx ;
bx *
bx 3
bx <
b0x %
x&
bx 0
bx :
bx (
bx '
bx 1
bx 9
bx 8
bx 7
bx +
bx 6
b1000000 .
b1000000 5
1"
