ALU_RISCV.v
`timescale 1ns / 1ps

module Alu_riscv(
    input [31:0] a,
    input [31:0] b,
    input [4:0] aluOp,
    output reg flag,
    output reg [31:0] result 
    );
    
    `define ALU_ADD 5'b00000
    `define ALU_SUB 5'b00001 
    `define ALU_XOR 5'b00010
    `define ALU_OR  5'b00011
    `define ALU_AND 5'b00100  
    `define ALU_SRA 5'b00101
    `define ALU_SRL 5'b00110
    `define ALU_SLL 5'b00111
    `define ALU_LTS 5'b01000
    `define ALU_LTU 5'b01001
    `define ALU_GES 5'b01010
    `define ALU_GEU 5'b01011
    `define ALU_EQ  5'b01100
    `define ALU_NE  5'b01101      
    
    always @ (*) begin
        case(aluOp)
            `ALU_ADD : begin result = a + b; flag = 0; end
            `ALU_SUB : begin result = a - b; flag = 0; end
            `ALU_XOR : begin result = a ^ b; flag = 0; end
            `ALU_OR : begin result = a | b; flag = 0; end
            `ALU_AND : begin result = a & b; flag = 0; end
            `ALU_SRA : begin result = a >>> b; flag = 0; end
            `ALU_SRL : begin result = a >> b; flag = 0; end
            `ALU_SLL : begin result = a << b; flag = 0; end
            `ALU_LTS : begin result = $signed(a) < $signed(b); flag = ($signed(a) < $signed(b)); end
            `ALU_LTU : begin result = a < b; flag = (a < b); end
            `ALU_GES : begin result = $signed(a) >= $signed(b); flag = ($signed(a) >= $signed(b)); end
            `ALU_GEU : begin result = a >= b; flag = (a >= b); end
            `ALU_EQ : begin result = a == b; flag = (a == b); end
            `ALU_NE : begin result = a != b; flag = (a != b); end
            default: begin result = 6'hxx; flag = 1'bx; end
        endcase
    end
    
endmodule

RF.v
`timescale 1ns / 1ps

module RF(
    input clk, //Clock signal
    input we3, //Write Enable 
    input [4:0] a1, //Adress port 1
    input [4:0] a2, //Adress port 2
    input [4:0] a3, //Adress port 3
    input [31:0] wd3, //Write Data
    input rst,
    
    output [31:0] rd1, //Read Data1
    output [31:0] rd2 //Read Data1
    );
    
    //Main register
    reg [31:0] rf [0:31];

    assign rd1 = (a1 != 0) ? rf[a1] : 0;
    assign rd2 = (a2 != 0) ? rf[a2] : 0;   
 
    integer i;

    always @ (posedge clk)
        if (rst) begin 
            for (i=0; i<31; i=i+1) begin
               rf[i] <= 32'd0;
            end
        end 
        else begin
            if (we3) rf[a3] <= wd3;
        end
        

endmodule

instruction_memory.v
`timescale 1ns / 1ps


module instruction_memory(
    input [7:0] a,
    output [31:0] rd
    );
    
    initial $readmemb("file_name", reg_name);
    reg [31:0] reg_name [63:0];
    
    assign rd = reg_name[a];
    
endmodule

microarchitecture.v
`timescale 1ns / 1ps

`include "instruction_memory.v"
`include "ALU_RISCV.v"
`include "RF.v"

module microarchitecture(
    input clk,
    input rst,
    input [31:0] sw,

    output [31:0] out
);

    wire [31:0] instr; //All instruction

    //Write enable
    wire we3; 
    assign we3 = instr[29] | instr [28]; 
    
    wire [31:0] rd1; //Read data from RF port 1
    wire [31:0] rd2; //Read data from RF port 2
    reg [31:0] wd3; //Write data from RF port 3
    
    reg [7:0] pc; //Register for Program Counter
    
    wire [31:0] aluResult; //ALU result
    wire flag; //ALU flag

    assign out = aluResult[31:0];
   
    wire [1:0] pcOp;
    assign pcOp = ((flag & instr[30])) | instr[31];
    reg [7:0] pcInput;
    
    //Work with program counter
    always @ (*) begin
        case(pcOp)
            2'b0: begin pcInput = 8'h1; end
            2'b1: begin pcInput = instr[12:5]; end
        endcase    
    end
    
    //Increase program counter
    always @ (posedge clk | rst) begin
        if (rst) begin
            pc <= 0;
        end
        else begin
            pc <= pc + pcInput;
        end
    end
    
    //Instantiation of modules ALU, RF, Instruction memory
    instruction_memory IM (pc, instr);
    RF finalRF(clk, we3, instr[22:18], instr[17:13], instr[4:0], wd3, rst, rd1, rd2);
    Alu_riscv ALU(rd1, rd2, instr[27:23], flag, aluResult);
    
    //Work with write data
    wire [1:0] wdOp = instr[29:28];
    wire [31:0] seConst = {{9{instr[27]}}, instr[27:5]}; //SE 
    
    //Multiplexor for write register file
    always @ (*) begin
        case(wdOp)
            2'd1: begin assign wd3 = sw; end
            2'd3: begin assign wd3 = aluResult; end
            2'd2: begin assign wd3 = seConst; end
        endcase
    end
    
endmodule

microarchitecture_tb.v
`timescale 1ns / 1ps
`include "microarchitecture.v"

module microarchitecture_tb();

    reg [31:0] sw = 32'd0;

    reg clk = 1'b1;
    always #1 clk = !clk;

    reg rst = 1'b1;
    
    wire [31:0] out;

    microarchitecture microarchitecture(clk, rst, sw, out);

    initial begin
        rst = 1'b1;
        #10
        rst = 1'b0;
        $dumpfile("RESULT.vcd");
        $dumpvars;
        #300 
        $display("Result: ",out);
        $finish;
    end
endmodule

RESULT.vcd
$date
	Sat Nov 20 21:11:47 2021
$end
$version
	Icarus Verilog
$end
$timescale
	1ps
$end
$scope module microarchitecture_tb $end
$var wire 32 ! out [31:0] $end
$var reg 1 " clk $end
$var reg 1 # rst $end
$var reg 32 $ sw [31:0] $end
$scope module microarchitecture $end
$var wire 1 " clk $end
$var wire 32 % out [31:0] $end
$var wire 2 & pcOp [1:0] $end
$var wire 1 # rst $end
$var wire 32 ' sw [31:0] $end
$var wire 1 ( we3 $end
$var wire 2 ) wdOp [1:0] $end
$var wire 32 * seConst [31:0] $end
$var wire 32 + rd2 [31:0] $end
$var wire 32 , rd1 [31:0] $end
$var wire 32 - instr [31:0] $end
$var wire 1 . flag $end
$var wire 32 / aluResult [31:0] $end
$var reg 8 0 pc [7:0] $end
$var reg 8 1 pcInput [7:0] $end
$var reg 32 2 wd3 [31:0] $end
$scope module ALU $end
$var wire 5 3 aluOp [4:0] $end
$var wire 32 4 b [31:0] $end
$var wire 32 5 a [31:0] $end
$var reg 1 . flag $end
$var reg 32 6 result [31:0] $end
$upscope $end
$scope module IM $end
$var wire 8 7 a [7:0] $end
$var wire 32 8 rd [31:0] $end
$upscope $end
$scope module finalRF $end
$var wire 5 9 a1 [4:0] $end
$var wire 5 : a2 [4:0] $end
$var wire 5 ; a3 [4:0] $end
$var wire 1 " clk $end
$var wire 1 # rst $end
$var wire 32 < wd3 [31:0] $end
$var wire 1 ( we3 $end
$var wire 32 = rd2 [31:0] $end
$var wire 32 > rd1 [31:0] $end
$var integer 32 ? i [31:0] $end
$upscope $end
$upscope $end
$upscope $end
$enddefinitions $end
#10000
$dumpvars
b11111 ?
b0 >
b0 =
b0 <
b10 ;
b0 :
b0 9
b10000000000000000000000000010 8
b0 7
b0 6
b0 5
b0 4
b0 3
b0 2
b1 1
b0 0
b0 /
0.
b10000000000000000000000000010 -
b0 ,
b0 +
b0 *
b1 )
1(
b0 '
b0 &
b0 %
b0 $
0#
1"
b0 !
$end
#11000
0"
#12000
b1 2
b1 <
b1 *
b10 )
b1 ;
b100000000000000000000000100001 -
b100000000000000000000000100001 8
b1 0
b1 7
1"
#13000
0"
#14000
b11 ;
b100000000000000000000000100011 -
b100000000000000000000000100011 8
b10 0
b10 7
1"
#15000
0"
#16000
b100 ;
b100000000000000000000000100100 -
b100000000000000000000000100100 8
b11 0
b11 7
1"
#17000
0"
#18000
b10 !
b10 %
b10 /
b10 6
b1 +
b1 4
b1 =
b1 ,
b1 5
b1 >
b10 2
b10 <
b110000100000000 *
b11 )
b11 ;
b1 :
b11 9
b110000000011000010000000000011 -
b110000000011000010000000000011 8
b100 0
b100 7
1"
#19000
0"
#20000
b0 +
b0 4
b0 =
b0 !
b0 %
b1 2
b1 <
b0 /
b0 6
b1 *
b10 )
b101 ;
b0 :
b0 9
b0 ,
b0 5
b0 >
b100000000000000000000000100101 -
b100000000000000000000000100101 8
b101 0
b101 7
1"
#21000
0"
#22000
b1 !
b1 %
b1 /
b1 6
b1 +
b1 4
b1 =
b1 2
b1 <
b10000000000 *
b11 )
b110 ;
b100 :
b110000000000001000000000000110 -
b110000000000001000000000000110 8
b110 0
b110 7
1"
#23000
0"
#24000
b101 1
b1 &
1.
b10 +
b10 4
b10 =
0(
b1000000100001100000101 *
b0 )
b1000 3
b0 ;
b11 :
b10 9
b1000100000010000110000010100000 -
b1000100000010000110000010100000 8
b111 0
b111 7
1"
#25000
0"
#26000
0.
b0 +
b0 4
b0 =
b1 ,
b1 5
b1 >
1(
b1000000000000000 *
b11 )
b0 3
b100 ;
b0 :
b100 9
b0 1
b10110000000100000000000000000100 -
b10110000000100000000000000000100 8
b1100 0
b1100 7
1"
