ALU_RISCV.v
`timescale 1ns / 1ps

module Alu_riscv(
    input [31:0] a,
    input [31:0] b,
    input [4:0] aluOp,
    output reg flag,
    output reg [31:0] result 
    );
    
    `define ALU_ADD 5'b00000
    `define ALU_SUB 5'b00001 
    `define ALU_XOR 5'b00010
    `define ALU_OR  5'b00011
    `define ALU_AND 5'b00100  
    `define ALU_SRA 5'b00101
    `define ALU_SRL 5'b00110
    `define ALU_SLL 5'b00111
    `define ALU_LTS 5'b01000
    `define ALU_LTU 5'b01001
    `define ALU_GES 5'b01010
    `define ALU_GEU 5'b01011
    `define ALU_EQ  5'b01100
    `define ALU_NE  5'b01101      
    
    always @ (*) begin
        case(aluOp)
            `ALU_ADD : begin result = a + b; flag = 0; end
            `ALU_SUB : begin result = a - b; flag = 0; end
            `ALU_XOR : begin result = a ^ b; flag = 0; end
            `ALU_OR : begin result = a | b; flag = 0; end
            `ALU_AND : begin result = a & b; flag = 0; end
            `ALU_SRA : begin result = a >>> b; flag = 0; end
            `ALU_SRL : begin result = a >> b; flag = 0; end
            `ALU_SLL : begin result = a << b; flag = 0; end
            `ALU_LTS : begin result = $signed(a) < $signed(b); flag = ($signed(a) < $signed(b)); end
            `ALU_LTU : begin result = a < b; flag = (a < b); end
            `ALU_GES : begin result = $signed(a) >= $signed(b); flag = ($signed(a) >= $signed(b)); end
            `ALU_GEU : begin result = a >= b; flag = (a >= b); end
            `ALU_EQ : begin result = a == b; flag = (a == b); end
            `ALU_NE : begin result = a != b; flag = (a != b); end
            default: begin result = 6'hxx; flag = 1'bx; end
        endcase
    end
    
endmodule

RF.v
`timescale 1ns / 1ps

module RF(
    input clk, //Clock signal
    input we3, //Write Enable 
    input [4:0] a1, //Adress port 1
    input [4:0] a2, //Adress port 2
    input [4:0] a3, //Adress port 3
    input [31:0] wd3, //Write Data
    input rst,
    
    output [31:0] rd1, //Read Data1
    output [31:0] rd2 //Read Data1
    );
    
    //Main register
    reg [31:0] rf [0:31];

    assign rd1 = (a1 != 0) ? rf[a1] : 0;
    assign rd2 = (a2 != 0) ? rf[a2] : 0;   
 
    integer i;

    always @ (posedge clk)
        if (rst) begin 
            for (i=0; i<31; i=i+1) begin
               rf[i] <= 32'd0;
            end
        end 
        else begin
            if (we3) rf[a3] <= wd3;
        end
        

endmodule

instruction_memory.v
`timescale 1ns / 1ps


module instruction_memory(
    input [7:0] a,
    output [31:0] rd
    );
    
    initial $readmemb("file_name", reg_name);
    reg [31:0] reg_name [63:0];
    
    assign rd = reg_name[a];
    
endmodule

Source/microarchitecture.v
`timescale 1ns / 1ps

`include "instruction_memory.v"
`include "ALU_RISCV.v"
`include "RF.v"

module microarchitecture(
    input clk,
    input rst,
    input [31:0] sw,

    output [31:0] out
);

    wire [31:0] instr; //All instruction

    //Write enable
    wire we3; 
    assign we3 = instr[29] | instr [28]; 
    
    wire [31:0] rd1; //Read data from RF port 1
    wire [31:0] rd2; //Read data from RF port 2
    reg [31:0] wd3; //Write data from RF port 3
    
    reg [7:0] pc; //Register for Program Counter
    
    wire [31:0] aluResult; //ALU result
    wire flag; //ALU flag

    assign out = aluResult[31:0];
   
    wire [1:0] pcOp;
    assign pcOp = ((flag & instr[30])) | instr[31];
    reg [7:0] pcInput;
    
    //Work with program counter
    always @ (*) begin
        case(pcOp)
            2'b0: begin pcInput = 8'h1; end
            2'b1: begin pcInput = instr[12:5]; end
        endcase    
    end
    
    //Increase program counter
    always @ (posedge clk or posedge rst) begin
        if (rst) begin
            pc <= 0;
        end
        else begin
            pc <= pc + pcInput;
        end
    end
    
    //Instantiation of modules ALU, RF, Instruction memory
    instruction_memory IM (pc, instr);
    RF finalRF(clk, we3, instr[22:18], instr[17:13], instr[4:0], wd3, rst, rd1, rd2);
    Alu_riscv ALU(rd1, rd2, instr[27:23], flag, aluResult);
    
    //Work with write data
    wire [1:0] wdOp = instr[29:28];
    wire [31:0] seConst = {{9{instr[27]}}, instr[27:5]}; //SE 
    
    //Multiplexor for write register file
    always @ (*) begin
        case(wdOp)
            2'd1: begin assign wd3 = sw; end
            2'd3: begin assign wd3 = aluResult; end
            2'd2: begin assign wd3 = seConst; end
        endcase
    end
    
endmodule

Source/microarchitecture_tb.v
`timescale 1ns / 1ps
`include "microarchitecture.v"

module microarchitecture_tb();

    reg [31:0] sw = 32'd5;

    reg clk = 1'b1;
    always #1 clk = !clk;

    reg rst = 1'b1;
    
    wire [31:0] out;

    microarchitecture microarchitecture(clk, rst, sw, out);

    initial begin
        rst = 1'b1;
        #10
        rst = 1'b0;
        $dumpfile("RESULT.vcd");
        $dumpvars;
        #4000
        $display("Result: ", out);
        $finish;
    end
endmodule

Source/RESULT.vcd
$date
	Sun Dec  5 18:20:35 2021
$end
$version
	Icarus Verilog
$end
$timescale
	1ps
$end
$scope module microarchitecture_tb $end
$var wire 32 ! out [31:0] $end
$var reg 1 " clk $end
$var reg 1 # rst $end
$var reg 32 $ sw [31:0] $end
$scope module microarchitecture $end
$var wire 1 " clk $end
$var wire 32 % out [31:0] $end
$var wire 2 & pcOp [1:0] $end
$var wire 1 # rst $end
$var wire 32 ' sw [31:0] $end
$var wire 1 ( we3 $end
$var wire 2 ) wdOp [1:0] $end
$var wire 32 * seConst [31:0] $end
$var wire 32 + rd2 [31:0] $end
$var wire 32 , rd1 [31:0] $end
$var wire 32 - instr [31:0] $end
$var wire 1 . flag $end
$var wire 32 / aluResult [31:0] $end
$var reg 8 0 pc [7:0] $end
$var reg 8 1 pcInput [7:0] $end
$var reg 32 2 wd3 [31:0] $end
$scope module ALU $end
$var wire 5 3 aluOp [4:0] $end
$var wire 32 4 b [31:0] $end
$var wire 32 5 a [31:0] $end
$var reg 1 . flag $end
$var reg 32 6 result [31:0] $end
$upscope $end
$scope module IM $end
$var wire 8 7 a [7:0] $end
$var wire 32 8 rd [31:0] $end
$upscope $end
$scope module finalRF $end
$var wire 5 9 a1 [4:0] $end
$var wire 5 : a2 [4:0] $end
$var wire 5 ; a3 [4:0] $end
$var wire 1 " clk $end
$var wire 1 # rst $end
$var wire 32 < wd3 [31:0] $end
$var wire 1 ( we3 $end
$var wire 32 = rd2 [31:0] $end
$var wire 32 > rd1 [31:0] $end
$var integer 32 ? i [31:0] $end
$upscope $end
$upscope $end
$upscope $end
$enddefinitions $end
#10000
$dumpvars
b11111 ?
b0 >
b0 =
b1 <
b1 ;
b0 :
b0 9
b100000000000000000000000100001 8
b1 7
b0 6
b0 5
b0 4
b0 3
b1 2
b1 1
b1 0
b0 /
0.
b100000000000000000000000100001 -
b0 ,
b0 +
b1 *
b10 )
1(
b101 '
b0 &
b0 %
b101 $
0#
1"
b0 !
$end
#11000
0"
#12000
b11 ;
b100000000000000000000000100011 -
b100000000000000000000000100011 8
b10 0
b10 7
1"
#13000
0"
#14000
b100 ;
b100000000000000000000000100100 -
b100000000000000000000000100100 8
b11 0
b11 7
1"
#15000
0"
#16000
b10 !
b10 %
b10 /
b10 6
b1 +
b1 4
b1 =
b1 ,
b1 5
b1 >
b10 2
b10 <
b110000100000000 *
b11 )
b11 ;
b1 :
b11 9
b110000000011000010000000000011 -
b110000000011000010000000000011 8
b100 0
b100 7
1"
#17000
0"
#18000
b0 !
b0 %
b0 /
b0 6
b1 2
b1 <
b0 +
b0 4
b0 =
b0 ,
b0 5
b0 >
b1 *
b10 )
b101 ;
b0 :
b0 9
b100000000000000000000000100101 -
b100000000000000000000000100101 8
b101 0
b101 7
1"
#19000
0"
#20000
b1 !
b1 %
b1 /
b1 6
b1 +
b1 4
b1 =
b1 2
b1 <
b10000000000 *
b11 )
b110 ;
b100 :
b110000000000001000000000000110 -
b110000000000001000000000000110 8
b110 0
b110 7
1"
#21000
0"
#22000
b0 !
b0 %
b0 2
b0 <
b0 /
b0 6
b10 +
b10 4
b10 =
b101 ,
b101 5
b101 >
0(
b1000000100001100000101 *
b0 )
b1000 3
b0 ;
b11 :
b10 9
b1000100000010000110000010100000 -
b1000100000010000110000010100000 8
b111 0
b111 7
1"
#23000
0"
#24000
b10 !
b10 %
b10 2
b10 <
b10 /
b10 6
b1 +
b1 4
b1 =
b1 ,
b1 5
b1 >
1(
b1000011000000000 *
b11 )
b0 3
b100 ;
b110 :
b100 9
b110000000100001100000000000100 -
b110000000100001100000000000100 8
b1000 0
b1000 7
1"
#25000
0"
#26000
b1010000100000000 *
b101 ;
b1 :
b101 9
b110000000101000010000000000101 -
b110000000101000010000000000101 8
b1001 0
b1001 7
1"
#27000
0"
#28000
b11111010 1
b1 &
1.
b1 !
b1 %
b1 2
b1 <
b1 /
b1 6
b10 +
b10 4
b10 =
0(
b10 ,
b10 5
b10 >
b1100000110010111111010 *
b0 )
b1100 3
b0 ;
b101 :
b11 9
b1000110000011001011111101000000 -
b1000110000011001011111101000000 8
b1010 0
b1010 7
1"
#29000
0"
#30000
b0 &
0.
b11 !
b11 %
b11 2
b11 <
b11 /
b11 6
b1 +
b1 4
b1 =
1(
b110000100000000 *
b11 )
b0 3
b11 ;
b1 :
b1 1
b110000000011000010000000000011 -
b110000000011000010000000000011 8
b100 0
b100 7
1"
#31000
0"
#32000
b0 !
b0 %
b0 /
b0 6
b1 2
b1 <
b0 +
b0 4
b0 =
b0 ,
b0 5
b0 >
b1 *
b10 )
b101 ;
b0 :
b0 9
b100000000000000000000000100101 -
b100000000000000000000000100101 8
b101 0
b101 7
1"
#33000
0"
#34000
b10 !
b10 %
b10 /
b10 6
b10 +
b10 4
b10 =
b10 2
b10 <
b10000000000 *
b11 )
b110 ;
b100 :
b110000000000001000000000000110 -
b110000000000001000000000000110 8
b110 0
b110 7
1"
#35000
0"
#36000
b0 !
b0 %
b0 2
b0 <
b0 /
b0 6
b11 +
b11 4
b11 =
b101 ,
b101 5
b101 >
0(
b1000000100001100000101 *
b0 )
b1000 3
b0 ;
b11 :
b10 9
b1000100000010000110000010100000 -
b1000100000010000110000010100000 8
b111 0
b111 7
1"
#37000
0"
#38000
b100 !
b100 %
b100 2
b100 <
b100 /
b100 6
b10 +
b10 4
b10 =
b10 ,
b10 5
b10 >
1(
b1000011000000000 *
b11 )
b0 3
b100 ;
b110 :
b100 9
b110000000100001100000000000100 -
b110000000100001100000000000100 8
b1000 0
b1000 7
1"
#39000
0"
#40000
b10 !
b10 %
b10 2
b10 <
b10 /
b10 6
b1 +
b1 4
b1 =
b1 ,
b1 5
b1 >
b1010000100000000 *
b101 ;
b1 :
b101 9
b110000000101000010000000000101 -
b110000000101000010000000000101 8
b1001 0
b1001 7
1"
#41000
0"
#42000
b0 !
b0 %
b0 2
b0 <
b0 /
b0 6
b10 +
b10 4
b10 =
0(
b11 ,
b11 5
b11 >
b1100000110010111111010 *
b0 )
b1100 3
b0 ;
b101 :
b11 9
b1000110000011001011111101000000 -
b1000110000011001011111101000000 8
b1010 0
b1010 7
1"
#43000
0"
#44000
b11111101 1
b0 +
b0 4
b0 =
b0 ,
b0 5
b0 >
b1 &
b11111101 *
b0 3
b0 :
b0 9
b10000000000000000001111110100000 -
b10000000000000000001111110100000 8
b1011 0
b1011 7
1"
#45000
0"
#46000
b110 !
b110 %
b110 2
b110 <
b110 /
b110 6
b10 +
b10 4
b10 =
b100 ,
b100 5
b100 >
b0 &
1(
b1000011000000000 *
b11 )
b100 ;
b110 :
b100 9
b1 1
b110000000100001100000000000100 -
b110000000100001100000000000100 8
b1000 0
b1000 7
1"
#47000
0"
#48000
b11 !
b11 %
b11 2
b11 <
b11 /
b11 6
b1 +
b1 4
b1 =
b10 ,
b10 5
b10 >
b1010000100000000 *
b101 ;
b1 :
b101 9
b110000000101000010000000000101 -
b110000000101000010000000000101 8
b1001 0
b1001 7
1"
#49000
0"
#50000
b11111010 1
b1 &
1.
b1 !
b1 %
b1 2
b1 <
b1 /
b1 6
b11 +
b11 4
b11 =
0(
b11 ,
b11 5
b11 >
b1100000110010111111010 *
b0 )
b1100 3
b0 ;
b101 :
b11 9
b1000110000011001011111101000000 -
b1000110000011001011111101000000 8
b1010 0
b1010 7
1"
#51000
0"
#52000
b0 &
0.
b100 !
b100 %
b100 2
b100 <
b100 /
b100 6
b1 +
b1 4
b1 =
1(
b110000100000000 *
b11 )
b0 3
b11 ;
b1 :
b1 1
b110000000011000010000000000011 -
b110000000011000010000000000011 8
b100 0
b100 7
1"
#53000
0"
#54000
b0 !
b0 %
b0 /
b0 6
b1 2
b1 <
b0 +
b0 4
b0 =
b0 ,
b0 5
b0 >
b1 *
b10 )
b101 ;
b0 :
b0 9
b100000000000000000000000100101 -
b100000000000000000000000100101 8
b101 0
b101 7
1"
#55000
0"
#56000
b110 !
b110 %
b110 /
b110 6
b110 +
b110 4
b110 =
b110 2
b110 <
b10000000000 *
b11 )
b110 ;
b100 :
b110000000000001000000000000110 -
b110000000000001000000000000110 8
b110 0
b110 7
1"
#57000
0"
#58000
b0 !
b0 %
b0 2
b0 <
b0 /
b0 6
b100 +
b100 4
b100 =
b101 ,
b101 5
b101 >
0(
b1000000100001100000101 *
b0 )
b1000 3
b0 ;
b11 :
b10 9
b1000100000010000110000010100000 -
b1000100000010000110000010100000 8
b111 0
b111 7
1"
#59000
0"
#60000
b1100 !
b1100 %
b1100 2
b1100 <
b1100 /
b1100 6
b110 +
b110 4
b110 =
b110 ,
b110 5
b110 >
1(
b1000011000000000 *
b11 )
b0 3
b100 ;
b110 :
b100 9
b110000000100001100000000000100 -
b110000000100001100000000000100 8
b1000 0
b1000 7
1"
#61000
0"
#62000
b10 !
b10 %
b10 2
b10 <
b10 /
b10 6
b1 +
b1 4
b1 =
b1 ,
b1 5
b1 >
b1010000100000000 *
b101 ;
b1 :
b101 9
b110000000101000010000000000101 -
b110000000101000010000000000101 8
b1001 0
b1001 7
1"
#63000
0"
#64000
b0 !
b0 %
b0 2
b0 <
b0 /
b0 6
b10 +
b10 4
b10 =
0(
b100 ,
b100 5
b100 >
b1100000110010111111010 *
b0 )
b1100 3
b0 ;
b101 :
b11 9
b1000110000011001011111101000000 -
b1000110000011001011111101000000 8
b1010 0
b1010 7
1"
#65000
0"
#66000
b11111101 1
b0 +
b0 4
b0 =
b0 ,
b0 5
b0 >
b1 &
b11111101 *
b0 3
b0 :
b0 9
b10000000000000000001111110100000 -
b10000000000000000001111110100000 8
b1011 0
b1011 7
1"
#67000
0"
#68000
b10010 !
b10010 %
b10010 2
b10010 <
b10010 /
b10010 6
b110 +
b110 4
b110 =
b1100 ,
b1100 5
b1100 >
b0 &
1(
b1000011000000000 *
b11 )
b100 ;
b110 :
b100 9
b1 1
b110000000100001100000000000100 -
b110000000100001100000000000100 8
b1000 0
b1000 7
1"
#69000
0"
#70000
b11 !
b11 %
b11 2
b11 <
b11 /
b11 6
b1 +
b1 4
b1 =
b10 ,
b10 5
b10 >
b1010000100000000 *
b101 ;
b1 :
b101 9
b110000000101000010000000000101 -
b110000000101000010000000000101 8
b1001 0
b1001 7
1"
#71000
0"
#72000
b0 !
b0 %
b0 2
b0 <
b0 /
b0 6
b11 +
b11 4
b11 =
0(
b100 ,
b100 5
b100 >
b1100000110010111111010 *
b0 )
b1100 3
b0 ;
b101 :
b11 9
b1000110000011001011111101000000 -
b1000110000011001011111101000000 8
b1010 0
b1010 7
1"
#73000
0"
#74000
b11111101 1
b0 +
b0 4
b0 =
b0 ,
b0 5
b0 >
b1 &
b11111101 *
b0 3
b0 :
b0 9
b10000000000000000001111110100000 -
b10000000000000000001111110100000 8
b1011 0
b1011 7
1"
#75000
0"
#76000
b11000 !
b11000 %
b11000 2
b11000 <
b11000 /
b11000 6
b110 +
b110 4
b110 =
b10010 ,
b10010 5
b10010 >
b0 &
1(
b1000011000000000 *
b11 )
b100 ;
b110 :
b100 9
b1 1
b110000000100001100000000000100 -
b110000000100001100000000000100 8
b1000 0
b1000 7
1"
#77000
0"
#78000
b100 !
b100 %
b100 2
b100 <
b100 /
b100 6
b1 +
b1 4
b1 =
b11 ,
b11 5
b11 >
b1010000100000000 *
b101 ;
b1 :
b101 9
b110000000101000010000000000101 -
b110000000101000010000000000101 8
b1001 0
b1001 7
1"
#79000
0"
#80000
b11111010 1
b1 &
1.
b1 !
b1 %
b1 2
b1 <
b1 /
b1 6
b100 +
b100 4
b100 =
0(
b100 ,
b100 5
b100 >
b1100000110010111111010 *
b0 )
b1100 3
b0 ;
b101 :
b11 9
b1000110000011001011111101000000 -
b1000110000011001011111101000000 8
b1010 0
b1010 7
1"
#81000
0"
#82000
b0 &
0.
b101 !
b101 %
b101 2
b101 <
b101 /
b101 6
b1 +
b1 4
b1 =
1(
b110000100000000 *
b11 )
b0 3
b11 ;
b1 :
b1 1
b110000000011000010000000000011 -
b110000000011000010000000000011 8
b100 0
b100 7
1"
#83000
0"
#84000
b0 !
b0 %
b0 /
b0 6
b1 2
b1 <
b0 +
b0 4
b0 =
b0 ,
b0 5
b0 >
b1 *
b10 )
b101 ;
b0 :
b0 9
b100000000000000000000000100101 -
b100000000000000000000000100101 8
b101 0
b101 7
1"
#85000
0"
#86000
b11000 !
b11000 %
b11000 /
b11000 6
b11000 +
b11000 4
b11000 =
b11000 2
b11000 <
b10000000000 *
b11 )
b110 ;
b100 :
b110000000000001000000000000110 -
b110000000000001000000000000110 8
b110 0
b110 7
1"
#87000
0"
#88000
b0 !
b0 %
b0 2
b0 <
b0 /
b0 6
b101 +
b101 4
b101 =
b101 ,
b101 5
b101 >
0(
b1000000100001100000101 *
b0 )
b1000 3
b0 ;
b11 :
b10 9
b1000100000010000110000010100000 -
b1000100000010000110000010100000 8
b111 0
b111 7
1"
#89000
0"
#90000
b110000 !
b110000 %
b110000 2
b110000 <
b110000 /
b110000 6
b11000 +
b11000 4
b11000 =
b11000 ,
b11000 5
b11000 >
1(
b1000011000000000 *
b11 )
b0 3
b100 ;
b110 :
b100 9
b110000000100001100000000000100 -
b110000000100001100000000000100 8
b1000 0
b1000 7
1"
#91000
0"
#92000
b10 !
b10 %
b10 2
b10 <
b10 /
b10 6
b1 +
b1 4
b1 =
b1 ,
b1 5
b1 >
b1010000100000000 *
b101 ;
b1 :
b101 9
b110000000101000010000000000101 -
b110000000101000010000000000101 8
b1001 0
b1001 7
1"
#93000
0"
#94000
b0 !
b0 %
b0 2
b0 <
b0 /
b0 6
b10 +
b10 4
b10 =
0(
b101 ,
b101 5
b101 >
b1100000110010111111010 *
b0 )
b1100 3
b0 ;
b101 :
b11 9
b1000110000011001011111101000000 -
b1000110000011001011111101000000 8
b1010 0
b1010 7
1"
#95000
0"
#96000
b11111101 1
b0 +
b0 4
b0 =
b0 ,
b0 5
b0 >
b1 &
b11111101 *
b0 3
b0 :
b0 9
b10000000000000000001111110100000 -
b10000000000000000001111110100000 8
b1011 0
b1011 7
1"
#97000
0"
#98000
b1001000 !
b1001000 %
b1001000 2
b1001000 <
b1001000 /
b1001000 6
b11000 +
b11000 4
b11000 =
b110000 ,
b110000 5
b110000 >
b0 &
1(
b1000011000000000 *
b11 )
b100 ;
b110 :
b100 9
b1 1
b110000000100001100000000000100 -
b110000000100001100000000000100 8
b1000 0
b1000 7
1"
#99000
0"
#100000
b11 !
b11 %
b11 2
b11 <
b11 /
b11 6
b1 +
b1 4
b1 =
b10 ,
b10 5
b10 >
b1010000100000000 *
b101 ;
b1 :
b101 9
b110000000101000010000000000101 -
b110000000101000010000000000101 8
b1001 0
b1001 7
1"
#101000
0"
#102000
b0 !
b0 %
b0 2
b0 <
b0 /
b0 6
b11 +
b11 4
b11 =
0(
b101 ,
b101 5
b101 >
b1100000110010111111010 *
b0 )
b1100 3
b0 ;
b101 :
b11 9
b1000110000011001011111101000000 -
b1000110000011001011111101000000 8
b1010 0
b1010 7
1"
#103000
0"
#104000
b11111101 1
b0 +
b0 4
b0 =
b0 ,
b0 5
b0 >
b1 &
b11111101 *
b0 3
b0 :
b0 9
b10000000000000000001111110100000 -
b10000000000000000001111110100000 8
b1011 0
b1011 7
1"
#105000
0"
#106000
b1100000 !
b1100000 %
b1100000 2
b1100000 <
b1100000 /
b1100000 6
b11000 +
b11000 4
b11000 =
b1001000 ,
b1001000 5
b1001000 >
b0 &
1(
b1000011000000000 *
b11 )
b100 ;
b110 :
b100 9
b1 1
b110000000100001100000000000100 -
b110000000100001100000000000100 8
b1000 0
b1000 7
1"
#107000
0"
#108000
b100 !
b100 %
b100 2
b100 <
b100 /
b100 6
b1 +
b1 4
b1 =
b11 ,
b11 5
b11 >
b1010000100000000 *
b101 ;
b1 :
b101 9
b110000000101000010000000000101 -
b110000000101000010000000000101 8
b1001 0
b1001 7
1"
#109000
0"
#110000
b0 !
b0 %
b0 2
b0 <
b0 /
b0 6
b100 +
b100 4
b100 =
0(
b101 ,
b101 5
b101 >
b1100000110010111111010 *
b0 )
b1100 3
b0 ;
b101 :
b11 9
b1000110000011001011111101000000 -
b1000110000011001011111101000000 8
b1010 0
b1010 7
1"
#111000
0"
#112000
b11111101 1
b0 +
b0 4
b0 =
b0 ,
b0 5
b0 >
b1 &
b11111101 *
b0 3
b0 :
b0 9
b10000000000000000001111110100000 -
b10000000000000000001111110100000 8
b1011 0
b1011 7
1"
#113000
0"
#114000
b1111000 !
b1111000 %
b1111000 2
b1111000 <
b1111000 /
b1111000 6
b11000 +
b11000 4
b11000 =
b1100000 ,
b1100000 5
b1100000 >
b0 &
1(
b1000011000000000 *
b11 )
b100 ;
b110 :
b100 9
b1 1
b110000000100001100000000000100 -
b110000000100001100000000000100 8
b1000 0
b1000 7
1"
#115000
0"
#116000
b101 !
b101 %
b101 2
b101 <
b101 /
b101 6
b1 +
b1 4
b1 =
b100 ,
b100 5
b100 >
b1010000100000000 *
b101 ;
b1 :
b101 9
b110000000101000010000000000101 -
b110000000101000010000000000101 8
b1001 0
b1001 7
1"
#117000
0"
#118000
b11111010 1
b1 &
1.
b1 !
b1 %
b1 2
b1 <
b1 /
b1 6
b101 +
b101 4
b101 =
0(
b101 ,
b101 5
b101 >
b1100000110010111111010 *
b0 )
b1100 3
b0 ;
b101 :
b11 9
b1000110000011001011111101000000 -
b1000110000011001011111101000000 8
b1010 0
b1010 7
1"
#119000
0"
#120000
b0 &
0.
b110 !
b110 %
b110 2
b110 <
b110 /
b110 6
b1 +
b1 4
b1 =
1(
b110000100000000 *
b11 )
b0 3
b11 ;
b1 :
b1 1
b110000000011000010000000000011 -
b110000000011000010000000000011 8
b100 0
b100 7
1"
#121000
0"
#122000
b0 !
b0 %
b0 /
b0 6
b1 2
b1 <
b0 +
b0 4
b0 =
b0 ,
b0 5
b0 >
b1 *
b10 )
b101 ;
b0 :
b0 9
b100000000000000000000000100101 -
b100000000000000000000000100101 8
b101 0
b101 7
1"
#123000
0"
#124000
b1111000 !
b1111000 %
b1111000 /
b1111000 6
b1111000 +
b1111000 4
b1111000 =
b1111000 2
b1111000 <
b10000000000 *
b11 )
b110 ;
b100 :
b110000000000001000000000000110 -
b110000000000001000000000000110 8
b110 0
b110 7
1"
#125000
0"
#126000
b101 1
b1 &
1.
b1 !
b1 %
b1 2
b1 <
b1 /
b1 6
b110 +
b110 4
b110 =
b101 ,
b101 5
b101 >
0(
b1000000100001100000101 *
b0 )
b1000 3
b0 ;
b11 :
b10 9
b1000100000010000110000010100000 -
b1000100000010000110000010100000 8
b111 0
b111 7
1"
#127000
0"
#128000
0.
b1111000 !
b1111000 %
b1111000 2
b1111000 <
b1111000 /
b1111000 6
b0 +
b0 4
b0 =
b1111000 ,
b1111000 5
b1111000 >
1(
b1000000000000000 *
b11 )
b0 3
b100 ;
b0 :
b100 9
b0 1
b10110000000100000000000000000100 -
b10110000000100000000000000000100 8
b1100 0
b1100 7
1"
